spider/SPIDER.py
spider/__init__.py
spider/clustering.py
spider/enrichment.py
spider/preprocess.py
spider/svi.py
spider/trajectory.py
spider/util.py
spider/version.py
spider/visualization.py
spider/R_script/__init__.py
spider/R_script/run_SPARKX.R
spider/R_script/run_nnSVG.R
spider/R_script/run_spatalk.R
spider/SpatialDE/__init__.py
spider/SpatialDE/aeh.py
spider/SpatialDE/de_test.py
spider/SpatialDE/dp_hmrf.py
spider/SpatialDE/gaussian_process.py
spider/SpatialDE/io.py
spider/SpatialDE/svca.py
spider/SpatialDE/_internal/__init__.py
spider/SpatialDE/_internal/distance_cache.py
spider/SpatialDE/_internal/gpflow_helpers.py
spider/SpatialDE/_internal/kernels.py
spider/SpatialDE/_internal/models.py
spider/SpatialDE/_internal/optimizer.py
spider/SpatialDE/_internal/score_test.py
spider/SpatialDE/_internal/sm_kernel.py
spider/SpatialDE/_internal/svca.py
spider/SpatialDE/_internal/tf_dataset.py
spider/SpatialDE/_internal/util.py
spider/SpatialDE/_internal/util_mixture.py
spider/lrdb/__init__.py
spiderYa-0.1.7.dist-info/LICENSE
spiderYa-0.1.7.dist-info/METADATA
spiderYa-0.1.7.dist-info/WHEEL
spiderYa-0.1.7.dist-info/top_level.txt
spiderYa-0.1.7.dist-info/RECORD
