Metadata-Version: 2.1
Name: spiderYa
Version: 0.1.7
Summary: Identifying spatially variable interactions
Home-page: https://github.com/deepomicslab/SPIDER
Author: Li Shiying
Author-email: shiyingli7-c@my.cityu.edu.hk
Classifier: Programming Language :: Python :: 3
Classifier: License :: OSI Approved :: MIT License
Classifier: Operating System :: OS Independent
License-File: LICENSE
Requires-Dist: anndata (>=0.8.0)
Requires-Dist: numpy
Requires-Dist: Cython
Requires-Dist: cellrank
Requires-Dist: fa2
Requires-Dist: gseapy
Requires-Dist: h5py
Requires-Dist: igraph
Requires-Dist: leidenalg
Requires-Dist: louvain
Requires-Dist: matplotlib
Requires-Dist: matplotlib-venn
Requires-Dist: networkx
Requires-Dist: numba
Requires-Dist: pandas
Requires-Dist: plotly
Requires-Dist: pygco
Requires-Dist: scanpy
Requires-Dist: scgco
Requires-Dist: scikit-learn
Requires-Dist: scipy
Requires-Dist: scvelo
Requires-Dist: seaborn
Requires-Dist: somde
Requires-Dist: somoclu
Requires-Dist: spatialde
Requires-Dist: stlearn
Requires-Dist: umap-learn
Requires-Dist: statsmodels
Requires-Dist: scprep
Requires-Dist: squidpy
Requires-Dist: magic-impute
Requires-Dist: NaiveDE
Requires-Dist: gpflow
Requires-Dist: tensorflow (>=2.12)
